MattZeta/MattZeta.py
MattZeta/__init__.py
MattZeta-0.2.dist-info/METADATA
MattZeta-0.2.dist-info/WHEEL
MattZeta-0.2.dist-info/top_level.txt
MattZeta-0.2.dist-info/RECORD
