Metadata-Version: 2.1
Name: MattZeta
Version: 0.2
Summary: ZETA test for neurons, more faster.
Author-email: Matthew Perkins <matthew.perkins@mssm.edu>
Project-URL: Homepage, https://github.com/matthewperkins/MattZeta
Project-URL: Bug Tracker, https://github.com/matthewperkins/MattZeta/issues
Classifier: 
Requires-Python: >=3.8
Requires-Dist: numpy
Requires-Dist: matplotlib
Requires-Dist: scipy
Requires-Dist: numba
